{
    "domain": "cdnkimg.com",
    "owner": {},
    "source": [
        "DuckDuckGo-US"
    ],
    "prevalence": 0.00125,
    "sites": 175,
    "subdomains": [
        "i"
    ],
    "cnames": [],
    "fingerprinting": 0,
    "resources": [
        {
            "rule": "cdnkimg\\.com\\/auto\\/192\\/image\\/vk\\/7974\\/974\\/621ceb6957e8ct1646062441r9009\\.jpeg",
            "cookies": 0,
            "fingerprinting": 0,
            "subdomains": [
                "i"
            ],
            "apis": {},
            "sites": 4,
            "prevalence": 0.0000286,
            "cnames": [],
            "responseHashes": [
                "5c6b723f2b284b7d157584c7174deb30823525c37fc84313bd835b5a6cf21195"
            ],
            "type": "Image",
            "firstPartyCookies": {},
            "firstPartyCookiesSent": {},
            "exampleSites": [
                "severeporn.com",
                "terceiroz.com",
                "www.pornyoung.me"
            ]
        },
        {
            "rule": "cdnkimg\\.com\\/auto\\/192\\/image\\/vk\\/7823\\/823\\/621ce88233680t1646061698r8974\\.jpeg",
            "cookies": 0,
            "fingerprinting": 0,
            "subdomains": [
                "i"
            ],
            "apis": {},
            "sites": 3,
            "prevalence": 0.0000214,
            "cnames": [],
            "responseHashes": [
                "5c6b723f2b284b7d157584c7174deb30823525c37fc84313bd835b5a6cf21195"
            ],
            "type": "Image",
            "firstPartyCookies": {},
            "firstPartyCookiesSent": {},
            "exampleSites": [
                "allindiansex.asia",
                "bestindiantube.com",
                "desivdo.com"
            ]
        },
        {
            "rule": "cdnkimg\\.com\\/auto\\/192\\/image\\/tesr\\/3209\\/209\\/6220851044366t1646298384r8942\\.jpg",
            "cookies": 0,
            "fingerprinting": 0,
            "subdomains": [
                "i"
            ],
            "apis": {},
            "sites": 3,
            "prevalence": 0.0000214,
            "cnames": [],
            "responseHashes": [
                "494dc5965cbd975171e483ebd8a49074748a723209ef15c8fd3dc975c999ced6"
            ],
            "type": "Image",
            "firstPartyCookies": {},
            "firstPartyCookiesSent": {},
            "exampleSites": [
                "animetoday.online",
                "gtorrent.xyz",
                "muzzo.ru"
            ]
        },
        {
            "rule": "cdnkimg\\.com\\/auto\\/192\\/image\\/vk\\/1050\\/50\\/61ae407907f9ft1638809721r4446\\.png",
            "cookies": 0,
            "fingerprinting": 0,
            "subdomains": [
                "i"
            ],
            "apis": {},
            "sites": 7,
            "prevalence": 0.00005,
            "cnames": [],
            "responseHashes": [
                "16d635188855ffd04d362a80d2e1a044824d83b80a1f69df9c40a162041f210e"
            ],
            "type": "Image",
            "firstPartyCookies": {},
            "firstPartyCookiesSent": {},
            "exampleSites": [
                "asian-mom-sex.com",
                "pornocaseiro.vlog.br",
                "www.meuscontoseroticos.eco.br",
                "www.novinhavideosporno.com",
                "www.xmom.me",
                "www.xnxxxvideoshd.com",
                "xhamsters.top"
            ]
        },
        {
            "rule": "cdnkimg\\.com\\/auto\\/400\\/image\\/tesr\\/2119\\/119\\/621fc35674deat1646248790r4759\\.jpeg",
            "cookies": 0,
            "fingerprinting": 0,
            "subdomains": [
                "i"
            ],
            "apis": {},
            "sites": 3,
            "prevalence": 0.0000214,
            "cnames": [],
            "responseHashes": [
                "81c2768bb1249416780837ca26169f78d29d16adee08432e243e38d0b07434c8"
            ],
            "type": "Image",
            "firstPartyCookies": {},
            "firstPartyCookiesSent": {},
            "exampleSites": [
                "avtika.ru",
                "pozdravok.online",
                "warbook.club"
            ]
        },
        {
            "rule": "cdnkimg\\.com\\/auto\\/492x328\\/image\\/tesr\\/1839\\/839\\/rect_621f7042b6ee2t1646227522r7452\\.jpg",
            "cookies": 0,
            "fingerprinting": 0,
            "subdomains": [
                "i"
            ],
            "apis": {},
            "sites": 2,
            "prevalence": 0.0000143,
            "cnames": [],
            "responseHashes": [
                "868abe11296fd5924842a235102647f7fc7416f71fd9dbdf5f1d8925a0bfb1c6"
            ],
            "type": "Image",
            "firstPartyCookies": {},
            "firstPartyCookiesSent": {},
            "exampleSites": [
                "babenki.info",
                "coronavirus-control.ru"
            ]
        },
        {
            "rule": "cdnkimg\\.com\\/auto\\/492x328\\/image\\/vk\\/2480\\/480\\/rect_62173b17f3ea0t1645689623r5718\\.jpg",
            "cookies": 0,
            "fingerprinting": 0,
            "subdomains": [
                "i"
            ],
            "apis": {},
            "sites": 12,
            "prevalence": 0.0000858,
            "cnames": [],
            "responseHashes": [
                "ce41e625b79b98901016d8c3d44032fc79520def793adbbbc8d2fb0907ad5213"
            ],
            "type": "Image",
            "firstPartyCookies": {},
            "firstPartyCookiesSent": {},
            "exampleSites": [
                "beautifulhairypussy.com",
                "bokepjepang234.com",
                "desi52.cc",
                "famousinternetgirlsgalleries.com",
                "film-adult.org",
                "hairypussypix.com",
                "porn765.org",
                "teen-nudist.top",
                "www.crazysexstory.com",
                "www.italianoxxx.com",
                "www.voyeurex.com",
                "xnxx2.top"
            ]
        },
        {
            "rule": "cdnkimg\\.com\\/auto\\/192\\/image\\/vk\\/2480\\/480\\/62173b17f3ea0t1645689623r5718\\.jpg",
            "cookies": 0,
            "fingerprinting": 0,
            "subdomains": [
                "i"
            ],
            "apis": {},
            "sites": 12,
            "prevalence": 0.0000858,
            "cnames": [],
            "responseHashes": [
                "ab55c5b041a524a8377701b44dbf04e4f826ec18c49741da8128caccb7d9d9ad"
            ],
            "type": "Image",
            "firstPartyCookies": {},
            "firstPartyCookiesSent": {},
            "exampleSites": [
                "beautifulhairypussy.com",
                "bokepjepang234.com",
                "desi52.cc",
                "famousinternetgirlsgalleries.com",
                "film-adult.org",
                "hairypussypix.com",
                "porn765.org",
                "teen-nudist.top",
                "www.crazysexstory.com",
                "www.italianoxxx.com",
                "www.voyeurex.com",
                "xnxx2.top"
            ]
        },
        {
            "rule": "cdnkimg\\.com\\/auto\\/492x328\\/image\\/vk\\/2477\\/477\\/rect_62173a83596dft1645689475r3431\\.jpg",
            "cookies": 0,
            "fingerprinting": 0,
            "subdomains": [
                "i"
            ],
            "apis": {},
            "sites": 17,
            "prevalence": 0.000122,
            "cnames": [],
            "responseHashes": [
                "90b95c3f0324034b35eeb40d5e33449a754517ff30210c8c12454ce0f301c14f"
            ],
            "type": "Image",
            "firstPartyCookies": {},
            "firstPartyCookiesSent": {},
            "exampleSites": [
                "bestnudecelebs.net",
                "bokepz234.net",
                "boypornvideo.com",
                "dankwank.net",
                "desipornphoto.com",
                "hotchicks.tv",
                "jungespornovideo.com",
                "mydesi.xyz",
                "onlyfansforum.famousinternetgirls.com",
                "porn765.org",
                "subindojav.xyz",
                "tubedupe.com",
                "upornia.com",
                "www.perverttube.com",
                "www.xxxcom.asia",
                "xnxx.city",
                "xxxsex.rocks"
            ]
        },
        {
            "rule": "cdnkimg\\.com\\/auto\\/192\\/image\\/vk\\/2477\\/477\\/62173a83596dft1645689475r3431\\.jpg",
            "cookies": 0,
            "fingerprinting": 0,
            "subdomains": [
                "i"
            ],
            "apis": {},
            "sites": 17,
            "prevalence": 0.000122,
            "cnames": [],
            "responseHashes": [
                "174c9777989ee3ef808364db79fbbe112d2458cc9d9dc7eae7b5450dcf4cacf5"
            ],
            "type": "Image",
            "firstPartyCookies": {},
            "firstPartyCookiesSent": {},
            "exampleSites": [
                "bestnudecelebs.net",
                "bokepz234.net",
                "boypornvideo.com",
                "dankwank.net",
                "desipornphoto.com",
                "hotchicks.tv",
                "jungespornovideo.com",
                "mydesi.xyz",
                "onlyfansforum.famousinternetgirls.com",
                "porn765.org",
                "subindojav.xyz",
                "tubedupe.com",
                "upornia.com",
                "www.perverttube.com",
                "www.xxxcom.asia",
                "xnxx.city",
                "xxxsex.rocks"
            ]
        },
        {
            "rule": "cdnkimg\\.com\\/auto\\/492x328\\/image\\/vk\\/2478\\/478\\/rect_62173aa3c4828t1645689507r7947\\.jpg",
            "cookies": 0,
            "fingerprinting": 0,
            "subdomains": [
                "i"
            ],
            "apis": {},
            "sites": 11,
            "prevalence": 0.0000786,
            "cnames": [],
            "responseHashes": [
                "56f5961a28d0a9b5f2c285f6e9f4848492ce8962e8f6bd79bea34a9488720ac7"
            ],
            "type": "Image",
            "firstPartyCookies": {},
            "firstPartyCookiesSent": {},
            "exampleSites": [
                "bokepla.com",
                "bokepz789.org",
                "boombo.biz",
                "cat3movie.org",
                "hotdesigirlsfuck.com",
                "javforme.ninja",
                "pornokissi.org",
                "upornia.com",
                "vjav.tube",
                "www.xmegadrive.com",
                "xnxx2.top"
            ]
        },
        {
            "rule": "cdnkimg\\.com\\/auto\\/192\\/image\\/vk\\/2478\\/478\\/62173aa3c4828t1645689507r7947\\.jpg",
            "cookies": 0,
            "fingerprinting": 0,
            "subdomains": [
                "i"
            ],
            "apis": {},
            "sites": 11,
            "prevalence": 0.0000786,
            "cnames": [],
            "responseHashes": [
                "ee35e771abddee37dc3102223d3cd1d623634a1bf60eac23ffbb9d4bd69fa996"
            ],
            "type": "Image",
            "firstPartyCookies": {},
            "firstPartyCookiesSent": {},
            "exampleSites": [
                "bokepla.com",
                "bokepz789.org",
                "boombo.biz",
                "cat3movie.org",
                "hotdesigirlsfuck.com",
                "javforme.ninja",
                "pornokissi.org",
                "upornia.com",
                "vjav.tube",
                "www.xmegadrive.com",
                "xnxx2.top"
            ]
        },
        {
            "rule": "cdnkimg\\.com\\/auto\\/492x328\\/image\\/vk\\/2481\\/481\\/rect_62173b3aebdcet1645689658r4191\\.jpg",
            "cookies": 0,
            "fingerprinting": 0,
            "subdomains": [
                "i"
            ],
            "apis": {},
            "sites": 12,
            "prevalence": 0.0000858,
            "cnames": [],
            "responseHashes": [
                "21ffd01a13750acd87017c2d279f12dc2f7f56e0c614a45ad70c007d373c46ab"
            ],
            "type": "Image",
            "firstPartyCookies": {},
            "firstPartyCookiesSent": {},
            "exampleSites": [
                "bokepz234.net",
                "boobsis.com",
                "cartoonprn.com",
                "hentaiporno.xxx",
                "komiktap.in",
                "m.fuckup.xxx",
                "porn-image.net",
                "tubedupe.com",
                "vjav.tube",
                "www.amaporn.com",
                "www.toptamilsexvideos.com",
                "zbokephd.net"
            ]
        },
        {
            "rule": "cdnkimg\\.com\\/auto\\/192\\/image\\/vk\\/2481\\/481\\/62173b3aebdcet1645689658r4191\\.jpg",
            "cookies": 0,
            "fingerprinting": 0,
            "subdomains": [
                "i"
            ],
            "apis": {},
            "sites": 12,
            "prevalence": 0.0000858,
            "cnames": [],
            "responseHashes": [
                "c946e58ffda8ceda73c4c9190de9d1dab7440b62b8e2e8fde7a5fe9bb1f45bc4"
            ],
            "type": "Image",
            "firstPartyCookies": {},
            "firstPartyCookiesSent": {},
            "exampleSites": [
                "bokepz234.net",
                "boobsis.com",
                "cartoonprn.com",
                "hentaiporno.xxx",
                "komiktap.in",
                "m.fuckup.xxx",
                "porn-image.net",
                "tubedupe.com",
                "vjav.tube",
                "www.amaporn.com",
                "www.toptamilsexvideos.com",
                "zbokephd.net"
            ]
        },
        {
            "rule": "cdnkimg\\.com\\/auto\\/492x328\\/image\\/vk\\/2479\\/479\\/rect_62173adb151e7t1645689563r9226\\.png",
            "cookies": 0,
            "fingerprinting": 0,
            "subdomains": [
                "i"
            ],
            "apis": {},
            "sites": 8,
            "prevalence": 0.0000572,
            "cnames": [],
            "responseHashes": [
                "c14cc147c0e788963d65772aaec60f2a22a4b0663d1a99d7f679ee90f2b47379"
            ],
            "type": "Image",
            "firstPartyCookies": {},
            "firstPartyCookiesSent": {},
            "exampleSites": [
                "boobsis.com",
                "boombo.biz",
                "hclips.com",
                "javhdo.net",
                "porn300.us",
                "tabuporns.com",
                "www.3rab-naar.com",
                "www.onlyleaks.me"
            ]
        },
        {
            "rule": "cdnkimg\\.com\\/auto\\/192\\/image\\/vk\\/2479\\/479\\/62173adb151e7t1645689563r9226\\.png",
            "cookies": 0,
            "fingerprinting": 0,
            "subdomains": [
                "i"
            ],
            "apis": {},
            "sites": 8,
            "prevalence": 0.0000572,
            "cnames": [],
            "responseHashes": [
                "df6665853296026e7f8f8e852940e20635f3fc5a873c4e5e1b2c199299be81ca"
            ],
            "type": "Image",
            "firstPartyCookies": {},
            "firstPartyCookiesSent": {},
            "exampleSites": [
                "boobsis.com",
                "boombo.biz",
                "hclips.com",
                "javhdo.net",
                "porn300.us",
                "tabuporns.com",
                "www.3rab-naar.com",
                "www.onlyleaks.me"
            ]
        },
        {
            "rule": "cdnkimg\\.com\\/auto\\/150\\/image\\/tesr\\/2119\\/119\\/621fc35674deat1646248790r4759\\.jpeg",
            "cookies": 0,
            "fingerprinting": 0,
            "subdomains": [
                "i"
            ],
            "apis": {},
            "sites": 2,
            "prevalence": 0.0000143,
            "cnames": [],
            "responseHashes": [
                "433b8f35d219b6491cca263aeb46fc3f23e2c897ad55ad4f985a5c11b2f04691"
            ],
            "type": "Image",
            "firstPartyCookies": {},
            "firstPartyCookiesSent": {},
            "exampleSites": [
                "brazzers-tv.biz",
                "celebxxx.top"
            ]
        },
        {
            "rule": "cdnkimg\\.com\\/auto\\/192\\/image\\/vk\\/6281\\/281\\/6221ef49511f3t1646391113r8384\\.jpeg",
            "cookies": 0,
            "fingerprinting": 0,
            "subdomains": [
                "i"
            ],
            "apis": {},
            "sites": 5,
            "prevalence": 0.0000357,
            "cnames": [],
            "responseHashes": [
                "5c6b723f2b284b7d157584c7174deb30823525c37fc84313bd835b5a6cf21195"
            ],
            "type": "Image",
            "firstPartyCookies": {},
            "firstPartyCookiesSent": {},
            "exampleSites": [
                "bucetas.blog",
                "ruleporn.com",
                "www.crutpedia.xyz",
                "www.japanesesex35.com",
                "www.youngxxxtubes.com"
            ]
        },
        {
            "rule": "cdnkimg\\.com\\/auto\\/192\\/image\\/vk\\/7883\\/883\\/621ce9d860506t1646062040r9413\\.jpeg",
            "cookies": 0,
            "fingerprinting": 0,
            "subdomains": [
                "i"
            ],
            "apis": {},
            "sites": 4,
            "prevalence": 0.0000286,
            "cnames": [],
            "responseHashes": [
                "5c6b723f2b284b7d157584c7174deb30823525c37fc84313bd835b5a6cf21195"
            ],
            "type": "Image",
            "firstPartyCookies": {},
            "firstPartyCookiesSent": {},
            "exampleSites": [
                "buceteiro.com",
                "contoseroticos.blog.br",
                "newjavxxx.com",
                "www.xnxx-xvideos.net"
            ]
        },
        {
            "rule": "cdnkimg\\.com\\/auto\\/492x328\\/image\\/tesr\\/6433\\/433\\/rect_622205fc841bft1646396924r7638\\.jpeg",
            "cookies": 0,
            "fingerprinting": 0,
            "subdomains": [
                "i"
            ],
            "apis": {},
            "sites": 2,
            "prevalence": 0.0000143,
            "cnames": [],
            "responseHashes": [
                "7950405e38e8823bc368c0cd529000d79cb208a40427e5b737714eb35dfb4678"
            ],
            "type": "Image",
            "firstPartyCookies": {},
            "firstPartyCookiesSent": {},
            "exampleSites": [
                "coronavirus-control.ru",
                "nagih.biz"
            ]
        },
        {
            "rule": "cdnkimg\\.com\\/auto\\/192\\/image\\/vk\\/7791\\/791\\/621ce6b694eb3t1646061238r229\\.jpeg",
            "cookies": 0,
            "fingerprinting": 0,
            "subdomains": [
                "i"
            ],
            "apis": {},
            "sites": 2,
            "prevalence": 0.0000143,
            "cnames": [],
            "responseHashes": [
                "5c6b723f2b284b7d157584c7174deb30823525c37fc84313bd835b5a6cf21195"
            ],
            "type": "Image",
            "firstPartyCookies": {},
            "firstPartyCookiesSent": {},
            "exampleSites": [
                "desi-fuck.com",
                "jav-porn-tube.com"
            ]
        },
        {
            "rule": "cdnkimg\\.com\\/auto\\/192\\/image\\/vk\\/7792\\/792\\/621ce6f498f20t1646061300r5237\\.jpeg",
            "cookies": 0,
            "fingerprinting": 0,
            "subdomains": [
                "i"
            ],
            "apis": {},
            "sites": 4,
            "prevalence": 0.0000286,
            "cnames": [],
            "responseHashes": [
                "5c6b723f2b284b7d157584c7174deb30823525c37fc84313bd835b5a6cf21195"
            ],
            "type": "Image",
            "firstPartyCookies": {},
            "firstPartyCookiesSent": {},
            "exampleSites": [
                "desi-porn.org",
                "shemaleleaks.com",
                "superhentai.blog",
                "www.sexdug.com"
            ]
        },
        {
            "rule": "cdnkimg\\.com\\/auto\\/192\\/image\\/vk\\/6285\\/285\\/6221f05636eb0t1646391382r6626\\.jpeg",
            "cookies": 0,
            "fingerprinting": 0,
            "subdomains": [
                "i"
            ],
            "apis": {},
            "sites": 5,
            "prevalence": 0.0000357,
            "cnames": [],
            "responseHashes": [
                "5c6b723f2b284b7d157584c7174deb30823525c37fc84313bd835b5a6cf21195"
            ],
            "type": "Image",
            "firstPartyCookies": {},
            "firstPartyCookiesSent": {},
            "exampleSites": [
                "filmy4wap.vip",
                "flagrasamadoresbrasileiros.com",
                "maturetits.pro",
                "www.youngxxxtubes.com",
                "xxnx2.com"
            ]
        },
        {
            "rule": "cdnkimg\\.com\\/auto\\/192\\/image\\/vk\\/7808\\/808\\/621ce73049415t1646061360r5991\\.jpeg",
            "cookies": 0,
            "fingerprinting": 0,
            "subdomains": [
                "i"
            ],
            "apis": {},
            "sites": 2,
            "prevalence": 0.0000143,
            "cnames": [],
            "responseHashes": [
                "5c6b723f2b284b7d157584c7174deb30823525c37fc84313bd835b5a6cf21195"
            ],
            "type": "Image",
            "firstPartyCookies": {},
            "firstPartyCookiesSent": {},
            "exampleSites": [
                "fullxcinema.com",
                "pornbest.pro"
            ]
        },
        {
            "rule": "cdnkimg\\.com\\/auto\\/192\\/image\\/vk\\/7822\\/822\\/621ce85cc65cet1646061660r5894\\.jpeg",
            "cookies": 0,
            "fingerprinting": 0,
            "subdomains": [
                "i"
            ],
            "apis": {},
            "sites": 3,
            "prevalence": 0.0000214,
            "cnames": [],
            "responseHashes": [
                "5c6b723f2b284b7d157584c7174deb30823525c37fc84313bd835b5a6cf21195"
            ],
            "type": "Image",
            "firstPartyCookies": {},
            "firstPartyCookiesSent": {},
            "exampleSites": [
                "granny-porn.me",
                "swingerpornfun.com",
                "terceiroz.com"
            ]
        },
        {
            "rule": "cdnkimg\\.com\\/auto\\/192\\/image\\/tesr\\/2119\\/119\\/621fc35674deat1646248790r4759\\.jpeg",
            "cookies": 0,
            "fingerprinting": 0,
            "subdomains": [
                "i"
            ],
            "apis": {},
            "sites": 2,
            "prevalence": 0.0000143,
            "cnames": [],
            "responseHashes": [
                "7350cbc9c6648ee0e877c82747d35f3595be352d9d42292125d27d27c4153b42"
            ],
            "type": "Image",
            "firstPartyCookies": {},
            "firstPartyCookiesSent": {},
            "exampleSites": [
                "gtorrent.xyz",
                "muzzo.ru"
            ]
        },
        {
            "rule": "cdnkimg\\.com\\/auto\\/192\\/image\\/vk\\/7922\\/922\\/621cea521aae0t1646062162r8408\\.jpeg",
            "cookies": 0,
            "fingerprinting": 0,
            "subdomains": [
                "i"
            ],
            "apis": {},
            "sites": 2,
            "prevalence": 0.0000143,
            "cnames": [],
            "responseHashes": [
                "5c6b723f2b284b7d157584c7174deb30823525c37fc84313bd835b5a6cf21195"
            ],
            "type": "Image",
            "firstPartyCookies": {},
            "firstPartyCookiesSent": {},
            "exampleSites": [
                "indianporn360.com",
                "xage.me"
            ]
        },
        {
            "rule": "cdnkimg\\.com\\/auto\\/492x328\\/image\\/tesr\\/1837\\/837\\/rect_621f700b8bdd6t1646227467r3894\\.jpg",
            "cookies": 0,
            "fingerprinting": 0,
            "subdomains": [
                "i"
            ],
            "apis": {},
            "sites": 2,
            "prevalence": 0.0000143,
            "cnames": [],
            "responseHashes": [
                "e1eb9f7d7c3b754881f0153b79bfd65398def0b03525adc18e86fab751c06a1a"
            ],
            "type": "Image",
            "firstPartyCookies": {},
            "firstPartyCookiesSent": {},
            "exampleSites": [
                "indianporngirl.com",
                "rusonline.org"
            ]
        },
        {
            "rule": "cdnkimg\\.com\\/auto\\/192\\/image\\/vk\\/7842\\/842\\/621ce8fb7035ft1646061819r6179\\.jpeg",
            "cookies": 0,
            "fingerprinting": 0,
            "subdomains": [
                "i"
            ],
            "apis": {},
            "sites": 3,
            "prevalence": 0.0000214,
            "cnames": [],
            "responseHashes": [
                "5c6b723f2b284b7d157584c7174deb30823525c37fc84313bd835b5a6cf21195"
            ],
            "type": "Image",
            "firstPartyCookies": {},
            "firstPartyCookiesSent": {},
            "exampleSites": [
                "japanesexxx.me",
                "www.quadrinhosdesexo.com",
                "www.xnxxxvideoshd.com"
            ]
        },
        {
            "rule": "cdnkimg\\.com\\/auto\\/192\\/image\\/vk\\/7953\\/953\\/621ceae88db90t1646062312r6085\\.jpeg",
            "cookies": 0,
            "fingerprinting": 0,
            "subdomains": [
                "i"
            ],
            "apis": {},
            "sites": 2,
            "prevalence": 0.0000143,
            "cnames": [],
            "responseHashes": [
                "5c6b723f2b284b7d157584c7174deb30823525c37fc84313bd835b5a6cf21195"
            ],
            "type": "Image",
            "firstPartyCookies": {},
            "firstPartyCookiesSent": {},
            "exampleSites": [
                "javxxxvideos.com",
                "www.lesbsex.com"
            ]
        },
        {
            "rule": "cdnkimg\\.com\\/auto\\/400\\/image\\/tesr\\/4164\\/164\\/6220d02527121t1646317605r2016\\.jpg",
            "cookies": 0,
            "fingerprinting": 0,
            "subdomains": [
                "i"
            ],
            "apis": {},
            "sites": 3,
            "prevalence": 0.0000214,
            "cnames": [],
            "responseHashes": [
                "703b5d63ca2448648177122affcb191aff421b9e829f7e1900224f9b030be351"
            ],
            "type": "Image",
            "firstPartyCookies": {},
            "firstPartyCookiesSent": {},
            "exampleSites": [
                "meshok-sovetov.ru",
                "pozdravok.online",
                "sovets.net"
            ]
        },
        {
            "rule": "cdnkimg\\.com\\/auto\\/192\\/image\\/vk\\/7946\\/946\\/621ceaa72b874t1646062247r2793\\.jpeg",
            "cookies": 0,
            "fingerprinting": 0,
            "subdomains": [
                "i"
            ],
            "apis": {},
            "sites": 2,
            "prevalence": 0.0000143,
            "cnames": [],
            "responseHashes": [
                "5c6b723f2b284b7d157584c7174deb30823525c37fc84313bd835b5a6cf21195"
            ],
            "type": "Image",
            "firstPartyCookies": {},
            "firstPartyCookiesSent": {},
            "exampleSites": [
                "mom-porn.com",
                "xxxnew.sexy"
            ]
        },
        {
            "rule": "cdnkimg\\.com\\/auto\\/192\\/image\\/vk\\/7810\\/810\\/621ce7b2e7131t1646061490r2952\\.jpeg",
            "cookies": 0,
            "fingerprinting": 0,
            "subdomains": [
                "i"
            ],
            "apis": {},
            "sites": 2,
            "prevalence": 0.0000143,
            "cnames": [],
            "responseHashes": [
                "5c6b723f2b284b7d157584c7174deb30823525c37fc84313bd835b5a6cf21195"
            ],
            "type": "Image",
            "firstPartyCookies": {},
            "firstPartyCookiesSent": {},
            "exampleSites": [
                "seegore.com",
                "www.pornjapanese.me"
            ]
        },
        {
            "rule": "cdnkimg\\.com\\/auto\\/192\\/image\\/vk\\/7964\\/964\\/621ceb292158dt1646062377r5897\\.jpeg",
            "cookies": 0,
            "fingerprinting": 0,
            "subdomains": [
                "i"
            ],
            "apis": {},
            "sites": 2,
            "prevalence": 0.0000143,
            "cnames": [],
            "responseHashes": [
                "5c6b723f2b284b7d157584c7174deb30823525c37fc84313bd835b5a6cf21195"
            ],
            "type": "Image",
            "firstPartyCookies": {},
            "firstPartyCookiesSent": {},
            "exampleSites": [
                "slutpad.com",
                "xxxpornvideo.me"
            ]
        },
        {
            "rule": "cdnkimg\\.com\\/auto\\/400\\/image\\/tesr\\/4002\\/2\\/6220d1c73c234t1646318023r2962\\.jpg",
            "cookies": 0,
            "fingerprinting": 0,
            "subdomains": [
                "i"
            ],
            "apis": {},
            "sites": 2,
            "prevalence": 0.0000143,
            "cnames": [],
            "responseHashes": [
                "f9d4fa8ba542ba65139555297896dd334971246e122047d91bc9e83524d27ca8"
            ],
            "type": "Image",
            "firstPartyCookies": {},
            "firstPartyCookiesSent": {},
            "exampleSites": [
                "sovets.net",
                "warbook.club"
            ]
        },
        {
            "rule": "cdnkimg\\.com\\/auto\\/192\\/image\\/vk\\/7841\\/841\\/621ce8aca5a1ft1646061740r1666\\.jpeg",
            "cookies": 0,
            "fingerprinting": 0,
            "subdomains": [
                "i"
            ],
            "apis": {},
            "sites": 2,
            "prevalence": 0.0000143,
            "cnames": [],
            "responseHashes": [
                "5c6b723f2b284b7d157584c7174deb30823525c37fc84313bd835b5a6cf21195"
            ],
            "type": "Image",
            "firstPartyCookies": {},
            "firstPartyCookiesSent": {},
            "exampleSites": [
                "uncutwebseries.com",
                "www.xmom.me"
            ]
        },
        {
            "rule": "cdnkimg\\.com\\/auto\\/192\\/image\\/vk\\/7917\\/917\\/621cea1379d64t1646062099r7367\\.jpeg",
            "cookies": 0,
            "fingerprinting": 0,
            "subdomains": [
                "i"
            ],
            "apis": {},
            "sites": 2,
            "prevalence": 0.0000143,
            "cnames": [],
            "responseHashes": [
                "5c6b723f2b284b7d157584c7174deb30823525c37fc84313bd835b5a6cf21195"
            ],
            "type": "Image",
            "firstPartyCookies": {},
            "firstPartyCookiesSent": {},
            "exampleSites": [
                "casadoscontos.com.br",
                "www.koreanporn.pro"
            ]
        },
        {
            "rule": "cdnkimg\\.com\\/auto\\/192\\/image\\/vk\\/7809\\/809\\/621ce776da459t1646061430r502\\.jpeg",
            "cookies": 0,
            "fingerprinting": 0,
            "subdomains": [
                "i"
            ],
            "apis": {},
            "sites": 3,
            "prevalence": 0.0000214,
            "cnames": [],
            "responseHashes": [
                "015ca2d259236418fea78b59ca5e4f6c3da5f6ca242e549ac4bf962323ad0af9"
            ],
            "type": "Image",
            "firstPartyCookies": {},
            "firstPartyCookiesSent": {},
            "exampleSites": [
                "chinese-porn.me",
                "www.spermyporn.com",
                "xxnxx.fun"
            ]
        },
        {
            "rule": "cdnkimg\\.com\\/auto\\/192\\/image\\/vk\\/7821\\/821\\/621ce836ea3cft1646061622r5708\\.jpeg",
            "cookies": 0,
            "fingerprinting": 0,
            "subdomains": [
                "i"
            ],
            "apis": {},
            "sites": 2,
            "prevalence": 0.0000143,
            "cnames": [],
            "responseHashes": [
                "5c6b723f2b284b7d157584c7174deb30823525c37fc84313bd835b5a6cf21195"
            ],
            "type": "Image",
            "firstPartyCookies": {},
            "firstPartyCookiesSent": {},
            "exampleSites": [
                "lesbsex.com",
                "www.sexmature.me"
            ]
        }
    ],
    "categories": [],
    "performance": {},
    "cookies": 0,
    "types": {
        "Image": 202
    },
    "nameservers": [
        "pns102.cloudns.net",
        "pns101.cloudns.net",
        "pns103.cloudns.net",
        "pns104.cloudns.net"
    ]
}