{
    "domain": "chattigo.com",
    "owner": {},
    "source": [
        "DuckDuckGo-US"
    ],
    "prevalence": 0.0000544,
    "sites": 4,
    "subdomains": [
        "cdn-widgets",
        "cdn",
        "config-global"
    ],
    "cnames": [],
    "fingerprinting": 1,
    "resources": [
        {
            "rule": "chattigo\\.com\\/webchat-widget-new\\.js",
            "cookies": 0,
            "fingerprinting": 1,
            "subdomains": [
                "cdn-widgets"
            ],
            "apis": {
                "Navigator.prototype.userAgent": 2,
                "Animation.prototype.currentTime": 2,
                "Animation.prototype.startTime": 2,
                "window.localStorage": 3,
                "window.innerWidth": 2
            },
            "sites": 3,
            "prevalence": 0.0000408,
            "cnames": [],
            "responseHashes": [
                "fd1b80081429a78e45cb6ac3f2a4a953a81f932dd85e45db610ca10ae63faf68"
            ],
            "type": "Script",
            "firstPartyCookies": {},
            "firstPartyCookiesSent": {},
            "exampleSites": [
                "afphabitat.cl",
                "www.farmacenter.com.py",
                "www.starken.cl"
            ]
        },
        {
            "rule": "chattigo\\.com\\/css\\/chattigo-widget\\.css",
            "cookies": 0,
            "fingerprinting": 0,
            "subdomains": [
                "cdn"
            ],
            "apis": {},
            "sites": 4,
            "prevalence": 0.0000544,
            "cnames": [],
            "responseHashes": [
                "e6f46dce26f4d6651dbbef9fa09ff9cc1086c0bb006f58a396c077a564c9732f"
            ],
            "type": "Stylesheet",
            "firstPartyCookies": {},
            "firstPartyCookiesSent": {},
            "exampleSites": [
                "afphabitat.cl",
                "www.bancociudad.com.ar",
                "www.farmacenter.com.py",
                "www.starken.cl"
            ]
        },
        {
            "rule": "chattigo\\.com\\/assets\\/legacy\\/sounds\\/Rhea\\.mp3",
            "cookies": 0,
            "fingerprinting": 0,
            "subdomains": [
                "cdn"
            ],
            "apis": {},
            "sites": 4,
            "prevalence": 0.0000544,
            "cnames": [],
            "responseHashes": [
                "e83199cd474c321c4a84619e3b252d7d3e731b1c618422bc0042fc64c8dd0b95"
            ],
            "type": "Media",
            "firstPartyCookies": {},
            "firstPartyCookiesSent": {},
            "exampleSites": [
                "afphabitat.cl",
                "www.bancociudad.com.ar",
                "www.farmacenter.com.py",
                "www.starken.cl"
            ]
        },
        {
            "rule": "chattigo\\.com\\/atencionalclientefarmacenter1334-4811-webchat-wc-production\\.json",
            "cookies": 0,
            "fingerprinting": 0,
            "subdomains": [
                "config-global"
            ],
            "apis": {},
            "sites": 2,
            "prevalence": 0.0000272,
            "cnames": [],
            "responseHashes": [
                "3f8e25c705a61f9ef556f76710054c1703259135eecb008b13da7ecf8ca1f106"
            ],
            "type": "XHR",
            "firstPartyCookies": {},
            "firstPartyCookiesSent": {},
            "exampleSites": [
                "farmacenter.com.py",
                "www.farmacenter.com.py"
            ]
        }
    ],
    "categories": [],
    "performance": {},
    "cookies": 0,
    "topInitiators": [
        {
            "domain": "first party",
            "prevalence": 0.8
        },
        {
            "domain": "googletagmanager.com",
            "prevalence": 0.1
        },
        {
            "domain": "cloudflare.com",
            "prevalence": 0.1
        }
    ],
    "types": {
        "Script": 3,
        "Stylesheet": 4,
        "Media": 4,
        "XHR": 2
    },
    "nameservers": [
        "ns2.domain.com",
        "ns1.domain.com"
    ]
}