{
    "domain": "defybrick.com",
    "owner": {
        "name": "CHEQ AI Technologies Ltd.",
        "displayName": "CHEQ"
    },
    "source": [
        "DuckDuckGo-US"
    ],
    "prevalence": 0.00116,
    "sites": 85,
    "subdomains": [
        "rock",
        "flint"
    ],
    "cnames": [],
    "fingerprinting": 3,
    "resources": [
        {
            "rule": "defybrick\\.com\\/placement_invocation",
            "cookies": 0.0011,
            "fingerprinting": 3,
            "subdomains": [
                "rock"
            ],
            "apis": {
                "Navigator.prototype.platform": 82,
                "Navigator.prototype.vendor": 82,
                "Screen.prototype.width": 82,
                "Screen.prototype.height": 82,
                "Screen.prototype.availHeight": 82,
                "Screen.prototype.availWidth": 82,
                "Document.cookie getter": 81,
                "Navigator.prototype.userAgent": 82,
                "Navigator.prototype.onLine": 82,
                "Screen.prototype.colorDepth": 82,
                "Screen.prototype.pixelDepth": 82,
                "window.devicePixelRatio": 82,
                "Navigator.prototype.permissions": 80,
                "Navigator.prototype.webdriver": 80,
                "Navigator.prototype.plugins": 82,
                "Document.cookie setter": 81,
                "window.localStorage": 82,
                "Navigator.prototype.mimeTypes": 82,
                "window.innerWidth": 82,
                "HTMLCanvasElement.prototype.toDataURL": 82,
                "window.indexedDB": 82,
                "Navigator.prototype.doNotTrack": 82,
                "Navigator.prototype.maxTouchPoints": 82,
                "Navigator.prototype.hardwareConcurrency": 82,
                "window.screenTop": 82,
                "window.screenLeft": 82,
                "window.outerWidth": 82,
                "window.outerHeight": 82,
                "window.innerHeight": 82,
                "window.name": 82,
                "Performance.prototype.memory": 80,
                "Navigator.prototype.connection": 82,
                "Navigator.prototype.languages": 82,
                "HTMLMediaElement.prototype.canPlayType": 82,
                "Date.prototype.getTime": 82,
                "Date.prototype.getTimezoneOffset": 82,
                "PerformanceTiming.prototype.navigationStart": 82,
                "Navigator.prototype.productSub": 82,
                "Navigator.prototype.product": 82,
                "Navigator.prototype.appName": 82,
                "Navigator.prototype.appCodeName": 82,
                "Intl.DateTimeFormat.prototype.resolvedOptions": 82,
                "window.screenX": 82,
                "window.screenY": 82
            },
            "sites": 85,
            "prevalence": 0.00116,
            "cnames": [],
            "responseHashes": [
                "620bae4f435d4ccd1c611f602c0790871f65d6bf668f6ff2ac716b89285cdc4a",
                "417ec6b32ac3678c12ea58c75b954412c0dc6c76d37f66cef1fa820ddf8b4c69"
            ],
            "type": "Script",
            "firstPartyCookies": {
                "_cq_check": {
                    "ttl": -1673105718,
                    "length": 1,
                    "prevalence": 0.0011025808559294349,
                    "uniqueness": 0.012345679012345678
                }
            },
            "firstPartyCookiesSent": {},
            "exampleSites": [
                "justthenews.com",
                "www.gamosaurus.com",
                "forums.primetimer.com",
                "mail.rediff.com",
                "www.novelmtl.com",
                "www.novelmt.com",
                "petapixel.com",
                "mobile.srugim.co.il",
                "www.footballdb.com",
                "www.link4u.co.il",
                "f1mobile.rediff.com",
                "www.leaguesecretary.com",
                "portalebambini.it",
                "money.rediff.com",
                "f6mail.rediff.com",
                "www.sportnews.bz",
                "www.readwn.com",
                "www.suedtirolnews.it",
                "www.motorsport-total.com",
                "www.psychologies.com"
            ]
        },
        {
            "rule": "defybrick\\.com\\/show_pla",
            "cookies": 0,
            "fingerprinting": 0,
            "subdomains": [
                "flint"
            ],
            "apis": {},
            "sites": 83,
            "prevalence": 0.00113,
            "cnames": [],
            "responseHashes": [
                "f2a6d72046affd4134ee72fb1f4d0648c416f7dfc2a197834931c6242bd19535",
                "84b90dc404a38268d99e36e88ed919c26f4519f732ec983bb024be1aea46ea5a",
                "f5fe9d83563e7103d4404b3f2ceb97df6f62043d160bc3caf4a7899a617b3475",
                "e44c07083df9290ea833df92bfc04091847b8fbe55c7a5f770b8ab4b552371bf",
                "32ab0899f1a7e53f281c9a8ec2158c3b803f40cfe1143126cb1189f163d56c5a",
                "c8357e00f0b7537dbd21f5b743034ff5549b0d9b4709e60521cd6caa548ebf1c",
                "b5886cdbcf9770385750d7decf4980961650706c683e3c0549f100ba90c23b40",
                "55f89577e83ffd312b1db4dc5baaf556739a2259231e47bc3fe1c002d3572a28",
                "b8a7436919ad83347faf6b4e0faac1a21260cfe29b1263339ecbe9f3e59d8441",
                "e7894946f92b915bcc9342472539feef78156678ddfb72aafdb0e74c5c38b0da",
                "ddc2a21607a1c0048ba577053561c6cb886e06033fc0c998dda35de9ff377164",
                "5dc2f4a7173884152e7769b3138e11f99cf12e6cc4befb34304a983fc3f9ac26",
                "0a8181b8302ad7cf6d3dffd220767e68617bd8cec9de7b6029008b804e29e0de",
                "2953dfd26484c3285dc22c80915401dd22211e77393c9d33394ae0d74369e1af",
                "a8bbf287a5bc76a25bc3001a30b45ea0d31f949495dc30b9990b7f38f3d1d2e2",
                "0c49b13f254b0cc4c50f58b0208ab5cd356abcda097a7283dc1b454a8a480878",
                "8144346eb58988818b779ca931f349b31ee72ca874be6c143b136b206c14bb9f",
                "b31a6702c1f9cd260ae82f6d863c7850e7b5aac00465ca56778cadf98879e101",
                "a31f8d6a41513a52efc1949dcf5e3cbda392979c93aad5b6b7287a47f809853f",
                "b48f680db60e62ea05b9e5a8c3a913cd959ea9753dd91d43c05eaea7065b84ef",
                "48f68fcf741b920185cbf3568fe4a2719eb05cb698825b547ca0690a2a55a1fe",
                "7c77d9feab1d1c76caa1ef8b31935e3c7bf53f07b1d2638b39b63c127112ba07",
                "7707f9d834400ff2f367105fb4057849a5362fbc782180f4b2ea8b2284d1bc67",
                "4ee3933a12da278e1c6930607688921bc9081dcc38c8e75831f077b531973bef",
                "b55a610b7e587e07ce71c0b9c194e1d9b458690f8a67578e5a0e9aa43cc44c95",
                "93c52393f3b17d13f33f8d5176b503915f661dc122d85f9c12196226537b54b4",
                "4ba30a86ae8c55144c89b5088b5ff33d0e3b4f2a3b69d2b0f2c8919a78c5f069",
                "5948c89ff959817588579117dc4ba49a14df769ab183235dded54418fadca89f",
                "d2e89242d6b61992d46c18f99bb5f2b9af0f2860fda68ee5ae3d6a0d8ef4bbe1",
                "a5a612f529b328f78930eabd67a46f869dbb59a2ef6affdbda4969ff2b318df3",
                "73278405424aa3f881cdf37d7325c213fb216deb54c486804b6fc1b762f5b021",
                "d850adf4711ac74b496713f999bb69ea9783e0a236387ccaf542df7d88f82bc2",
                "7b55b40a2abd44aa0a00415edca86041096c6bf17c49bb180d10225a205426f4",
                "2340aecfea6ade60199986d7abedbcc835f15b5d913080c7eb7e85bddcd704f2",
                "52e808875eb51a7af37ffcbf32ab75658b713a72b243d846c455397cf708cbda",
                "786e42d415200e817aad503c4a1225f947d3587236dd2666e4e4b90f06f62269",
                "96e30acad2ab8ae42df4751d693e57abc8ef1b79d0de1b6f4bfb0c3edfb34a3a",
                "e35257f8a429908bcb7db5d85a6b94286b220ef0014c53eaf293ba962f1b133a",
                "a13e78cf1388b8d9cbf3838b4d9074955b6b07d95ba816ca31413070e00ae8af",
                "6f3e8588848292bdd4cc1b65a266e2a99d57ff946219477cd41d9bedef2f105b",
                "97d538c73abda82f74855b70d4f3d514a4f81b907e66c63c29a54b779b18dd85",
                "23e45e2437793e38c6e7c72024fe0e080664b37d88e5fecdbd5bd9fbac866bfd",
                "d108393e0d5e33f7ec49a44e4349093722e2d62059e5aec28e8d0838d13b9317",
                "050b37d1ac76c40d956f234957a1ff04331595e0efc0d3c265941d75be3877fa",
                "aa4b8d04af650366e6048050592b56b16b99227f14ad0230a62cac11f983ced7",
                "2ea0c90b5e094f4c1b197fac99cf42d2f4289efc527ecc1e71c5e05e50952d5f",
                "9448695683d1061d4b239c3d924ff550b10e66b224461dcd2261d05f0c0085cf",
                "85759ec4fac3131d65cc718e5edcbbb5a0e70445b7984dc9610c0b9c851dd9c4",
                "16042d0102e7432726b12b14848b6ab55dc38552c90ec80057ff01d2d1f66a62",
                "102d07e938a6d601b00135dee6f44313bbc0767f3d33b41db65b4fd82ebfbef2",
                "20a4aafb6f3632765941f2939795f28ad7faa78e3c76b46930b1b8ab0fe3ffe2",
                "18a4be2e76b147f76904e89c89ade567b1ca70e1e1ba563fad7a9a31f3d828cf",
                "8c8e44607c4ea2e4ea570abd4c5b6e669469967906246ceb01dd7eae67119552",
                "74dd154a2bc3a914b9e45b8429c58c0e50ee423560499b15df86491a9c1cf370",
                "4114347fe518c5706014d2fc60841a97b1198cacabe841851bbdf2d217908c18",
                "b38ba92db3dd162cf32870a3920e3c3c40d666bfe7f86901d2f48dd1d51016b4",
                "7ed37531b192306d74eedb0a85e4a7df16d2b95f66dfcadf98584c6127b1855b",
                "991386691a84e85d21c11e3ffe2569e93a15b048db838b8ee37fbe288ab0bc52",
                "007d0a9ce844eef2d690991cdace2b8623c003747a337490eadeb66998c33cd4",
                "eb7c4b11cd26030cd07e5b9a7b166622c9e2e22a2bcb50e7b1b110c0fb401b32",
                "196edb4927685079a7fc0c81c6ee6e61fd9accb81f36f128df7637b779bf9c2b",
                "223d90b441182854a3b082abf7f54b657ebe28eff0b6e523c8ada1a6cf8e655f",
                "f87a0220a49bb89d290fab224ac4c57061a07a2850972e038ddcfe865bd34b8a",
                "0c77c2f387b7fc1f0494c226304306c6ea1c67596058ddbff230a7948fcd59bd",
                "33c9f708e9d52604a402fe11aacebd171e612031bf494140250f05183ba91d9a",
                "b32486ef13c81baa99e379e4988a67089c5b5ca39ea9c8062c29609dcd6a01a4",
                "15d3092903eff8a9ff92ce81a0f4d99fa118de64404a127c4937427c7e3e15bb",
                "8671b483f74f3fe5fafb77e99770c6fbf1e19ca6b268526722777625fd597eef",
                "37af1c65c53b85ad55bf7bd5a907cba8b84ff22b0a45b39568a48a1bf9ce59f5",
                "17393617c4b2ddd5045ae351ddbcc8e4996aa9e549818c5f83c2b27508e26ea2",
                "3be9443ffbcd37d69dfc136b5925cb3320383962bb3b93ab77d9be1983f31c89",
                "2f37a207caba6bc22613e6023b185e5012496ee63d03648d8b9cfbd66365bffb",
                "be4a1c8f7ba7b127ce2b7502f691bb451a18c8acda77c9c442d9b0c47fbdb7bc",
                "845fd37201ef3784ef22f4d7d2647946168db239858add6cb30e2ddddb98fe00",
                "547c14740bcbd2c2a189114f886a4dbe0521907d295c72c64ae8a9d74b863a2f",
                "fbc56917f8e01259e45ed59ec47ddef0d94666a6365c32889e60b301313ed521",
                "ac35dcba2118b795debe2e40b693c60fe7914828f8bd5427e304bf57f00e5641",
                "2f2f64c2fa1d0eb10972711237764e5f0f4af9149aad4f8a6504adf21e66f89b"
            ],
            "type": "Script",
            "firstPartyCookies": {},
            "firstPartyCookiesSent": {
                "_li_dcdm_c": 0.000013612109332462159,
                "lotame_domain_check": 0.00006806054666231079,
                "__pid": 0.000013612109332462159
            },
            "exampleSites": [
                "www.sportnews.bz",
                "www.boursier.com",
                "www.wuxiax.com",
                "www.livefutbol.com",
                "f1mobile.rediff.com",
                "detaly.co.il",
                "www.myjoyonline.com",
                "m.famousfix.com",
                "lectortmo.com",
                "www.playboy.de",
                "www.wuxiamtl.com",
                "m.gpone.com",
                "www.lightnovelmeta.com",
                "www.rediff.com",
                "www.pokemoncoders.com",
                "www.footballdb.com",
                "www.turf-fr.com",
                "www.link4u.co.il",
                "portfolio.rediff.com",
                "www.srugim.co.il"
            ]
        },
        {
            "rule": "defybrick\\.com\\/tracker\\/imp\\.gif",
            "cookies": 0,
            "fingerprinting": 0,
            "subdomains": [
                "flint"
            ],
            "apis": {},
            "sites": 80,
            "prevalence": 0.00109,
            "cnames": [],
            "responseHashes": [
                "f4eef8263281c0b26486637831251059757bc3fdc4c3a48045a8ef8646b36e8f"
            ],
            "type": "Image",
            "firstPartyCookies": {},
            "firstPartyCookiesSent": {},
            "exampleSites": [
                "www.gamosaurus.com",
                "portalebambini.it",
                "www.allkpop.com",
                "portfolio.rediff.com",
                "www.psychologies.com",
                "www.wuxiamtl.com",
                "www.lightnovelmeta.com",
                "wap.business-standard.com",
                "www.enca.com",
                "f5mail.rediff.com",
                "beachgrit.com",
                "www.myjoyonline.com",
                "www.readwn.com",
                "www.canalturf.com",
                "www.infoplease.com",
                "www.cancioneros.com",
                "www.metro.pr",
                "money.rediff.com",
                "m.famousfix.com",
                "www.wuxiax.com"
            ]
        }
    ],
    "categories": [],
    "performance": {},
    "cookies": 0.0011,
    "topInitiators": [
        {
            "domain": "outbrain.com",
            "prevalence": 0.8828828828828829
        },
        {
            "domain": "adlightning.com",
            "prevalence": 0.05405405405405406
        },
        {
            "domain": "geoedge.be",
            "prevalence": 0.036036036036036036
        },
        {
            "domain": "first party",
            "prevalence": 0.02702702702702703
        }
    ],
    "types": {
        "Script": 168,
        "Image": 80
    },
    "nameservers": [
        "ns-1772.awsdns-29.co.uk",
        "ns-693.awsdns-22.net",
        "ns-48.awsdns-06.com",
        "ns-1078.awsdns-06.org"
    ]
}