{
    "domain": "notifica.re",
    "owner": {},
    "source": [
        "DuckDuckGo-US"
    ],
    "prevalence": 0.00005,
    "sites": 7,
    "subdomains": [
        "cloud",
        "cdn"
    ],
    "cnames": [],
    "fingerprinting": 1,
    "resources": [
        {
            "rule": "notifica\\.re\\/api\\/application\\/info",
            "cookies": 0,
            "fingerprinting": 0,
            "subdomains": [
                "cloud"
            ],
            "apis": {},
            "sites": 5,
            "prevalence": 0.0000357,
            "cnames": [],
            "responseHashes": [
                "32092ba383025959c5a33d7c7d2b721a4c6f8e72b97db54aa7b35d9fb76c35b3",
                "bebd047f4568326582568abf75f7ac643136e252fa1456d15b1c02f4710ebe53",
                "432058a55e56dac10354dc81b18f26bf5d48a7bd2761f1dd87e963c963178e0b"
            ],
            "type": "Fetch",
            "firstPartyCookies": {},
            "firstPartyCookiesSent": {},
            "exampleSites": [
                "ajax.nl",
                "www.ajax.nl",
                "www.claro.com.br",
                "www.net.com.br",
                "www.wefashion.nl"
            ]
        },
        {
            "rule": "notifica\\.re\\/api\\/application\\/info",
            "cookies": 0,
            "fingerprinting": 0,
            "subdomains": [
                "cloud"
            ],
            "apis": {},
            "sites": 5,
            "prevalence": 0.0000357,
            "cnames": [],
            "responseHashes": [],
            "type": "Preflight",
            "firstPartyCookies": {},
            "firstPartyCookiesSent": {},
            "exampleSites": [
                "ajax.nl",
                "www.ajax.nl",
                "www.claro.com.br",
                "www.net.com.br",
                "www.wefashion.nl"
            ]
        },
        {
            "rule": "notifica\\.re\\/libs\\/html5\\/v2\\/latest\\/notificare\\.min\\.js",
            "cookies": 0,
            "fingerprinting": 1,
            "subdomains": [
                "cdn"
            ],
            "apis": {
                "window.localStorage": 3,
                "Navigator.prototype.language": 3
            },
            "sites": 3,
            "prevalence": 0.0000214,
            "cnames": [],
            "responseHashes": [
                "5aa61442848583c60484e638c0206f8ee6449626df16fe55ece62e45b0e8339e"
            ],
            "type": "Script",
            "firstPartyCookies": {},
            "firstPartyCookiesSent": {},
            "exampleSites": [
                "claro.com.br",
                "www.claro.com.br",
                "www.net.com.br"
            ]
        },
        {
            "rule": "notifica\\.re\\/libs\\/html5\\/v2\\/latest\\/sw\\.js",
            "cookies": 0,
            "fingerprinting": 0,
            "subdomains": [
                "cdn"
            ],
            "apis": {},
            "sites": 3,
            "prevalence": 0.0000214,
            "cnames": [],
            "responseHashes": [
                "1c394fe27251d30b36f77e0d44a53ff560c2fedadb8a46cdb708592265c57317"
            ],
            "type": "Other",
            "firstPartyCookies": {},
            "firstPartyCookiesSent": {},
            "exampleSites": [
                "claro.com.br",
                "www.claro.com.br",
                "www.net.com.br"
            ]
        }
    ],
    "categories": [],
    "performance": {},
    "cookies": 0,
    "types": {
        "Fetch": 5,
        "Preflight": 5,
        "Script": 3,
        "Other": 3
    },
    "nameservers": [
        "ns-1352.awsdns-41.org",
        "ns-1544.awsdns-01.co.uk",
        "ns-392.awsdns-49.com",
        "ns-755.awsdns-30.net"
    ]
}