{
    "domain": "o2static.sk",
    "owner": {},
    "source": [
        "DuckDuckGo-US"
    ],
    "prevalence": 0.0000136,
    "sites": 1,
    "subdomains": [
        "www"
    ],
    "cnames": [],
    "fingerprinting": 3,
    "resources": [
        {
            "rule": "o2static\\.sk\\/combo\\/",
            "cookies": 0,
            "fingerprinting": 0,
            "subdomains": [
                "www"
            ],
            "apis": {},
            "sites": 2,
            "prevalence": 0.0000272,
            "cnames": [],
            "responseHashes": [
                "3ef77f4925d30662d22d2ab3ef623260f3c4222bf5fc717201726bf22817eb67"
            ],
            "type": "Script",
            "firstPartyCookies": {},
            "firstPartyCookiesSent": {},
            "exampleSites": [
                "o2.sk",
                "www.o2.sk"
            ]
        }
    ],
    "categories": [],
    "performance": {},
    "cookies": 0.0000136,
    "topInitiators": [
        {
            "domain": "first party",
            "prevalence": 1
        }
    ],
    "types": {
        "Script": 2
    },
    "nameservers": [
        "dns.iol.cz",
        "ns2.tel.cz"
    ]
}